pdf2md/__init__.py
pdf2md/parser.py
pdf2md/pile.py
pdf2md/syntax.py
pdf2md/writer.py
pdf2md-0.1.2.data/scripts/pdf2md
pdf2md-0.1.2.dist-info/LICENSE
pdf2md-0.1.2.dist-info/METADATA
pdf2md-0.1.2.dist-info/WHEEL
pdf2md-0.1.2.dist-info/top_level.txt
pdf2md-0.1.2.dist-info/RECORD
