Metadata-Version: 2.1
Name: pdf2md
Version: 0.1.2
Summary: Convert PDF files into markdown files
Home-page: https://github.com/runningBolin/pdf-to-markdown
Author: bolin
Author-email: runningBolin@gmail.com
License: New BSD License
Platform: UNKNOWN
License-File: LICENSE
Requires-Dist: pdfminer.six
